pytorch_fasterrcnn/__init__.py
pytorch_fasterrcnn/config.py
pytorch_fasterrcnn/crash_test.py
pytorch_fasterrcnn/dataset.py
pytorch_fasterrcnn/engine.py
pytorch_fasterrcnn/inference.py
pytorch_fasterrcnn/model.py
pytorch_fasterrcnn/train.py
pytorch_fasterrcnn/utils.py
pytorch_fasterrcnn-0.2.1.dist-info/LICENSE
pytorch_fasterrcnn-0.2.1.dist-info/METADATA
pytorch_fasterrcnn-0.2.1.dist-info/WHEEL
pytorch_fasterrcnn-0.2.1.dist-info/entry_points.txt
pytorch_fasterrcnn-0.2.1.dist-info/top_level.txt
pytorch_fasterrcnn-0.2.1.dist-info/RECORD
