Metadata-Version: 2.1
Name: pytorch-fasterrcnn
Version: 0.2.1
Summary: Torchvision Faster RCNN Fine Tuner
Home-page: https://github.com/oke-aditya/pytorch_fasterrcnn/tree/master/
Author: Aditya Oke
Author-email: okeaditya315@gmail.com
License: Apache Software License 2.0
Keywords: Python
Platform: UNKNOWN
Classifier: Development Status :: 5 - Production/Stable
Classifier: Intended Audience :: Developers
Classifier: License :: OSI Approved :: Apache Software License
Classifier: Natural Language :: English
Classifier: Programming Language :: Python :: 3.6
Classifier: Programming Language :: Python :: 3.7
Classifier: Programming Language :: Python :: 3.8
Requires-Python: >=3.6
Requires-Dist: numpy
